equilibrator_pathway/__init__.py
equilibrator_pathway/analysis_solution.py
equilibrator_pathway/cost_function.py
equilibrator_pathway/ecm_model.py
equilibrator_pathway/ecm_solution.py
equilibrator_pathway/mdf_solution.py
equilibrator_pathway/mdmc_solution.py
equilibrator_pathway/pathway.py
equilibrator_pathway/simulator.py
equilibrator_pathway/thermo_models.py
equilibrator_pathway/util.py
equilibrator_pathway-0.6.0.dist-info/LICENSE
equilibrator_pathway-0.6.0.dist-info/METADATA
equilibrator_pathway-0.6.0.dist-info/WHEEL
equilibrator_pathway-0.6.0.dist-info/top_level.txt
equilibrator_pathway-0.6.0.dist-info/zip-safe
equilibrator_pathway-0.6.0.dist-info/RECORD
