Metadata-Version: 2.1
Name: equilibrator-pathway
Version: 0.6.0
Summary: Pathway analysis tools by eQuilibrator
Author-email: Elad Noor <elad.noor@weizmann.ac.il>, "Moritz E. Beber" <midnighter@posteo.net>
License: MIT License
Project-URL: repository, https://gitlab.com/equilibrator/equilibrator-pathway/
Project-URL: documentation, https://equilibrator.readthedocs.io/en/latest/
Keywords: component contribution,Gibbs energy,biochemical reaction,eQuilibrator,enzyme cost minimization,max-min driving force
Classifier: Development Status :: 4 - Beta
Classifier: Intended Audience :: Science/Research
Classifier: Topic :: Scientific/Engineering :: Bio-Informatics
Classifier: Topic :: Scientific/Engineering :: Chemistry
Classifier: License :: OSI Approved :: MIT License
Classifier: Natural Language :: English
Classifier: Operating System :: OS Independent
Classifier: Programming Language :: Python :: 3 :: Only
Classifier: Programming Language :: Python :: 3.9
Classifier: Programming Language :: Python :: 3.10
Classifier: Programming Language :: Python :: 3.11
Classifier: Programming Language :: Python :: 3.12
Requires-Python: >=3.9
License-File: LICENSE
Requires-Dist: seaborn ~=0.13
Requires-Dist: cvxpy ~=1.4
Requires-Dist: sbtab >=1.0.8,~=1.0
Requires-Dist: matplotlib ~=3.8
Requires-Dist: equilibrator-api ~=0.6.0
Requires-Dist: equilibrator-cache ~=0.6.0
Provides-Extra: deployment
Requires-Dist: click ; extra == 'deployment'
Requires-Dist: click-log ; extra == 'deployment'
Requires-Dist: python-dateutil ; extra == 'deployment'
Requires-Dist: requests ; extra == 'deployment'
Requires-Dist: tqdm ; extra == 'deployment'
Provides-Extra: development
Requires-Dist: black ; extra == 'development'
Requires-Dist: isort ; extra == 'development'
Requires-Dist: flake8 ; extra == 'development'
Requires-Dist: safety ; extra == 'development'
Requires-Dist: tox ; extra == 'development'
Requires-Dist: twine ; extra == 'development'
Provides-Extra: test
Requires-Dist: pytest ; extra == 'test'
Requires-Dist: pytest-cov ; extra == 'test'
Requires-Dist: pytest-raises ; extra == 'test'
